ordeq_manifest/__init__.py
ordeq_manifest/_version.py
ordeq_manifest/manifest.py
ordeq_manifest/models.py
ordeq_manifest/py.typed
ordeq_manifest-1.1.0.dist-info/licenses/LICENSE
ordeq_manifest-1.1.0.dist-info/METADATA
ordeq_manifest-1.1.0.dist-info/WHEEL
ordeq_manifest-1.1.0.dist-info/top_level.txt
ordeq_manifest-1.1.0.dist-info/RECORD
