Metadata-Version: 2.4
Name: ordeq-manifest
Version: 1.1.0
Summary: Manifests for Ordeq projects
Author: Niels Neerhoff, Simon Brugman
Maintainer: Niels Neerhoff, Simon Brugman
License-Expression: MIT
Requires-Python: >=3.10
License-File: LICENSE
Requires-Dist: ordeq>=1.3.0
Requires-Dist: pydantic
Dynamic: license-file
